traductorkq/__init__.py
traductorkq-0.1.1.dist-info/WHEEL
traductorkq-0.1.1.dist-info/METADATA
traductorkq-0.1.1.dist-info/RECORD
